ragged/__init__.py
ragged/_helper_functions.py
ragged/_import.py
ragged/_spec_array_object.py
ragged/_spec_constants.py
ragged/_spec_creation_functions.py
ragged/_spec_data_type_functions.py
ragged/_spec_elementwise_functions.py
ragged/_spec_indexing_functions.py
ragged/_spec_linear_algebra_functions.py
ragged/_spec_manipulation_functions.py
ragged/_spec_searching_functions.py
ragged/_spec_set_functions.py
ragged/_spec_sorting_functions.py
ragged/_spec_statistical_functions.py
ragged/_spec_utility_functions.py
ragged/_typing.py
ragged/_version.py
ragged/_version.pyi
ragged/py.typed
ragged/io/__init__.py
ragged/io/cf.py
ragged-0.2.0.dist-info/METADATA
ragged-0.2.0.dist-info/WHEEL
ragged-0.2.0.dist-info/licenses/LICENSE
ragged-0.2.0.dist-info/RECORD
